{
  "started_at": "2025-10-29T13:08:13+05:30",
  "docker": {
    "postgres": { "port": 5433, "status": "running" },
    "redis": { "port": 6380, "status": "running" },
    "kafka": { "port": 9092, "status": "running" },
    "minio": { "port": 9000, "status": "running" }
  },
  "microservices": {
    "api_golang_v2": {
      "pid": 16624,
      "port": 3005,
      "description": "Import/Export API"
    },
    "product_service": {
      "pid": 16628,
      "port": 8001
    },
    "inventory_service": {
      "pid": 16635,
      "port": 8002
    },
    "sales_service": {
      "pid": 16643,
      "port": 8003
    },
    "api_gateway": {
      "pid": 16656,
      "port": 4000
    },
    "ai_service": {
      "pid": null,
      "port": 8010
    }
  },
  "frontend": {
    "pid": 17039,
    "port": 3000,
    "url": "http://localhost:3000"
  }
}
